{
  "code": 0,
  "msg": "获取成功",
  "data": [
    {
      "img": "https://img1.sycdn.imooc.com/szimg/5d1032ab08719e0906000338-360-202.jpg",
      "rate": 0,
      "type": "",
      "teacher": {
        "avatar": "https://img1.sycdn.imooc.com/user/5c38493b08230e7c07200720-100-100.jpg",
        "name": "咚咚呛"
      },
      "lastUpdate": "",
      "title": "编程必备基础知识 计算机组成原理+操作系统+计算机网络",
      "rank": "中级",
      "number": 1213,
      "comment": 36,
      "desc": "编程之前先学这门课，系统补足计算机基础知识，夯实编程地基",
      "isDiscount": false,
      "newPrice": "",
      "oldPrice": "236.00",
      "isLike": false
    },
    {
      "img": "https://img1.sycdn.imooc.com/szimg/5d3ff547091ba29712000676-360-202.jpg",
      "rate": 0,
      "type": "新课",
      "teacher": {
        "avatar": "https://img1.sycdn.imooc.com/user/559e32dd0001631209601280-100-100.jpg",
        "name": "Angelayuan"
      },
      "lastUpdate": "",
      "title": "专为程序员设计的统计课",
      "rank": "初级",
      "number": 83,
      "comment": 2,
      "desc": "完整清晰的统计学知识网络+与编程结合的讲解方式+数据可视化展示",
      "isDiscount": true,
      "newPrice": "226.00",
      "oldPrice": "266.00",
      "isLike": false
    },
    {
      "img": "https://img1.sycdn.imooc.com/szimg/5d31765d08c90cba06000338-360-202.jpg",
      "rate": 0,
      "type": "新课",
      "teacher": {
        "avatar": "https://img1.sycdn.imooc.com/user/5347593e00010cfb01400140-100-100.jpg",
        "name": "liuyubobobo"
      },
      "lastUpdate": "",
      "title": "玩转图论算法 大神带你从入门到精通（bobo老师爆款）",
      "rank": "中级",
      "number": 279,
      "comment": 12,
      "desc": "图论算法必学课程，带你从入门到精通，培养算法思维，提升内功水平",
      "isDiscount": true,
      "newPrice": "298.00",
      "oldPrice": "348.00",
      "isLike": true
    },
    {
      "img": "https://img1.sycdn.imooc.com/szimg/59b8a486000107fb05400300-360-202.jpg",
      "rate": 0,
      "type": "",
      "teacher": {
        "avatar": "https://img1.sycdn.imooc.com/user/54584e2c00010a2c02200220-100-100.jpg",
        "name": "7七月"
      },
      "lastUpdate": "",
      "title": "全面系统python3入门+进阶课程 零基础学python 小白也能听懂",
      "rank": "初级",
      "number": 9161,
      "comment": 1856,
      "desc": "0基础系统入门/语法精讲/配套练习+思考题/综合项目实践",
      "isDiscount": false,
      "newPrice": "",
      "oldPrice": "366.00",
      "isLike": false
    },
    {
      "img": "https://img1.sycdn.imooc.com/szimg/5c18d2d8000141c506000338-360-202.jpg",
      "rate": 0,
      "type": "热门",
      "teacher": {
        "avatar": "https://img1.sycdn.imooc.com/user/5c20a1bc0001b02506760800-100-100.jpg",
        "name": "xiangzepro"
      },
      "lastUpdate": "",
      "title": "剑指Java面试-Offer直通车",
      "rank": "中级",
      "number": 3962,
      "comment": 1136,
      "desc": "招聘季即将到来，让百度资深面试官来为你的高薪Offer保驾护航",
      "isDiscount": false,
      "newPrice": "",
      "oldPrice": "299.00",
      "isLike": false
    },
    {
      "img": "https://img1.sycdn.imooc.com/szimg/5d36a6000837a91d06000338-360-202.jpg",
      "rate": 67,
      "type": "新课",
      "teacher": {
        "avatar": "https://img1.sycdn.imooc.com/user/5abe468b0001664107390741-100-100.jpg",
        "name": "DellLee"
      },
      "lastUpdate": "",
      "title": "前端要学的测试课 从Jest入门到 TDD/BDD双实战",
      "rank": "中级",
      "number": 157,
      "comment": 6,
      "desc": "以Vue/React项目进行自动化测试实战，让你技术水平和架构思维双提升",
      "isDiscount": false,
      "newPrice": "",
      "oldPrice": "299.00",
      "isLike": false
    },
    {
      "img": "https://img1.sycdn.imooc.com/szimg/5d396b990811a64706000338-360-202.jpg",
      "rate": 0,
      "type": "新课",
      "teacher": {
        "avatar": "https://img1.sycdn.imooc.com/user/5b40c3d8000153d311101084-100-100.jpg",
        "name": "Sam"
      },
      "lastUpdate": "",
      "title": "前端要学的测试课 从Jest入门到 TDD/BDD双实战",
      "rank": "初级",
      "number": 64,
      "comment": 5,
      "desc": "最新 mpvue2.0 框架 - 实战小慕读书多平台小程序",
      "isDiscount": true,
      "newPrice": "226.00",
      "oldPrice": "266.00",
      "isLike": false
    },
    {
      "img": "https://img1.sycdn.imooc.com/szimg/5c7e6835087ef3d806000338-360-202.jpg",
      "rate": 0,
      "type": "热门",
      "teacher": {
        "avatar": "https://img1.sycdn.imooc.com/user/545847e20001163c02200220-100-100.jpg",
        "name": "CrazyCodeBoy"
      },
      "lastUpdate": "3天前",
      "title": "Flutter从入门到进阶 实战携程网App",
      "rank": "中级",
      "number": 1495,
      "comment": 383,
      "desc": "从入门到进阶，系统掌握Flutter开发核心技术",
      "isDiscount": false,
      "newPrice": "",
      "oldPrice": "348.00",
      "isLike": true
    },
    {
      "img": "https://img1.sycdn.imooc.com/szimg/5d08d0b308c9749706000338-360-202.jpg",
      "rate": 0,
      "type": "",
      "teacher": {
        "avatar": "https://img1.sycdn.imooc.com/user/5afe3d350001596a02430243-100-100.jpg",
        "name": "神思者l"
      },
      "lastUpdate": "",
      "title": "阿里新零售数据库设计与实战",
      "rank": "初级",
      "number": 551,
      "comment": 37,
      "desc": "数据库是开发人员的必修课，解锁“新零售”业务让数据库实战能力再上一层楼",
      "isDiscount": false,
      "newPrice": "",
      "oldPrice": "288.00",
      "isLike": false
    },
    {
      "img": "https://img1.sycdn.imooc.com/szimg/5d14215f08545a6b06000338-360-202.jpg",
      "rate": 0,
      "type": "热门",
      "teacher": {
        "avatar": "https://img1.sycdn.imooc.com/user/5d142f090804929712361209-100-100.jpg",
        "name": "大目"
      },
      "lastUpdate": "",
      "title": "Spring Cloud Alibaba微服务从入门到进阶",
      "rank": "高级",
      "number": 339,
      "comment": 21,
      "desc": "面向未来微服务:熟练掌握Spring Cloud Alibaba",
      "isDiscount": false,
      "newPrice": "",
      "oldPrice": "399.00",
      "isLike": false
    },
    {
      "img": "https://img1.sycdn.imooc.com/szimg/5d2e7ada09946f6f12000676-360-202.jpg",
      "rate": 0,
      "type": "新课",
      "teacher": {
        "avatar": "https://img1.sycdn.imooc.com/user/5c36c432000158e609600960-100-100.jpg",
        "name": "张勤一"
      },
      "lastUpdate": "2019.7.17",
      "title": "基于Spring Cloud微服务架构  广告系统设计与实现（经典升级）",
      "rank": "中级",
      "number": 905,
      "comment": 270,
      "desc": "掌握互联网广告系统，学会为公司创收，你自然就是最抢手的人才。可用于毕设。",
      "isDiscount": false,
      "newPrice": "",
      "oldPrice": "299.00",
      "isLike": false
    },
    {
      "img": "https://img1.sycdn.imooc.com/szimg/5d2820fd0874bbf806000338-360-202.jpg",
      "rate": 0,
      "type": "新课",
      "teacher": {
        "avatar": "https://img1.sycdn.imooc.com/user/57df9bcd000195e810231024-100-100.jpg",
        "name": "Mushishi_Xu"
      },
      "lastUpdate": "",
      "title": "Python接口自动化测试框架实战 从设计到开发",
      "rank": "中级",
      "number": 52,
      "comment": 2,
      "desc": "从基础开始掌握接口自动化测试框架的设计与开发，并教你如何开发桩服务 ",
      "isDiscount": false,
      "newPrice": "",
      "oldPrice": "299.00",
      "isLike": false
    },
    {
      "img": "https://img1.sycdn.imooc.com/szimg/5d25400a08fa408c06000338-360-202.jpg",
      "rate": 0,
      "type": "新课",
      "teacher": {
        "avatar": "https://img1.sycdn.imooc.com/user/5c20a1bc0001b02506760800-100-100.jpg",
        "name": "xiangzepro"
      },
      "lastUpdate": "2019.07.10",
      "title": "毕设神器 Java主流技术栈SSM+SpringBoot商铺系统（升级更新）",
      "rank": "初级",
      "number": 2587,
      "comment": 636,
      "desc": "SSM商铺系统V1.0，解决毕业设计痛点；SpringBoot商铺V2.0，满足企业工作刚需",
      "isDiscount": false,
      "newPrice": "",
      "oldPrice": "299.00",
      "isLike": false
    },
    {
      "img": "https://img1.sycdn.imooc.com/szimg/5d1eb552082e176e06000338-360-202.jpg",
      "rate": 0,
      "type": "新课",
      "teacher": {
        "avatar": "https://img1.sycdn.imooc.com/user/533e4d510001c2ad02000200-100-100.jpg",
        "name": "Michael__PK"
      },
      "lastUpdate": "",
      "title": "Spark进阶 大数据离线与实时项目实战",
      "rank": "中级",
      "number": 96,
      "comment": 6,
      "desc": "大数据生态圈中多个框架(Spark/Hbase/Redis/Hadoop)的整合应用及调优",
      "isDiscount": false,
      "newPrice": "",
      "oldPrice": "399.00",
      "isLike": false
    },
    {
      "img": "https://img1.sycdn.imooc.com/szimg/5d1ad17f08cd16e800000000-360-202.jpg",
      "rate": 0,
      "type": "",
      "teacher": {
        "avatar": "https://img1.sycdn.imooc.com/user/5cac7e810001fe7705270698-100-100.jpg",
        "name": "城南大师兄"
      },
      "lastUpdate": "",
      "title": "Zookeeper源码分析",
      "rank": "中级",
      "number": 59,
      "comment": 4,
      "desc": "“分而治之”逐一攻克Zookeeper框架各个组件的源码",
      "isDiscount": false,
      "newPrice": "",
      "oldPrice": "388.00",
      "isLike": false
    },
    {
      "img": "https://img1.sycdn.imooc.com/szimg/5d1032ab08719e0906000338-360-202.jpg",
      "rate": 0,
      "type": "",
      "teacher": {
        "avatar": "https://img1.sycdn.imooc.com/user/5c38493b08230e7c07200720-100-100.jpg",
        "name": "咚咚呛"
      },
      "lastUpdate": "",
      "title": "编程必备基础知识 计算机组成原理+操作系统+计算机网络",
      "rank": "中级",
      "number": 1213,
      "comment": 36,
      "desc": "编程之前先学这门课，系统补足计算机基础知识，夯实编程地基",
      "isDiscount": false,
      "newPrice": "",
      "oldPrice": "236.00",
      "isLike": false
    },
    {
      "img": "https://img1.sycdn.imooc.com/szimg/5d3ff547091ba29712000676-360-202.jpg",
      "rate": 0,
      "type": "新课",
      "teacher": {
        "avatar": "https://img1.sycdn.imooc.com/user/559e32dd0001631209601280-100-100.jpg",
        "name": "Angelayuan"
      },
      "lastUpdate": "",
      "title": "专为程序员设计的统计课",
      "rank": "初级",
      "number": 83,
      "comment": 2,
      "desc": "完整清晰的统计学知识网络+与编程结合的讲解方式+数据可视化展示",
      "isDiscount": true,
      "newPrice": "226.00",
      "oldPrice": "266.00",
      "isLike": false
    },
    {
      "img": "https://img1.sycdn.imooc.com/szimg/5d31765d08c90cba06000338-360-202.jpg",
      "rate": 0,
      "type": "新课",
      "teacher": {
        "avatar": "https://img1.sycdn.imooc.com/user/5347593e00010cfb01400140-100-100.jpg",
        "name": "liuyubobobo"
      },
      "lastUpdate": "",
      "title": "玩转图论算法 大神带你从入门到精通（bobo老师爆款）",
      "rank": "中级",
      "number": 279,
      "comment": 12,
      "desc": "图论算法必学课程，带你从入门到精通，培养算法思维，提升内功水平",
      "isDiscount": true,
      "newPrice": "298.00",
      "oldPrice": "348.00",
      "isLike": true
    },
    {
      "img": "https://img1.sycdn.imooc.com/szimg/59b8a486000107fb05400300-360-202.jpg",
      "rate": 0,
      "type": "",
      "teacher": {
        "avatar": "https://img1.sycdn.imooc.com/user/54584e2c00010a2c02200220-100-100.jpg",
        "name": "7七月"
      },
      "lastUpdate": "",
      "title": "全面系统python3入门+进阶课程 零基础学python 小白也能听懂",
      "rank": "初级",
      "number": 9161,
      "comment": 1856,
      "desc": "0基础系统入门/语法精讲/配套练习+思考题/综合项目实践",
      "isDiscount": false,
      "newPrice": "",
      "oldPrice": "366.00",
      "isLike": false
    },
    {
      "img": "https://img1.sycdn.imooc.com/szimg/5c18d2d8000141c506000338-360-202.jpg",
      "rate": 0,
      "type": "热门",
      "teacher": {
        "avatar": "https://img1.sycdn.imooc.com/user/5c20a1bc0001b02506760800-100-100.jpg",
        "name": "xiangzepro"
      },
      "lastUpdate": "",
      "title": "剑指Java面试-Offer直通车",
      "rank": "中级",
      "number": 3962,
      "comment": 1136,
      "desc": "招聘季即将到来，让百度资深面试官来为你的高薪Offer保驾护航",
      "isDiscount": false,
      "newPrice": "",
      "oldPrice": "299.00",
      "isLike": false
    },
    {
      "img": "https://img1.sycdn.imooc.com/szimg/5d36a6000837a91d06000338-360-202.jpg",
      "rate": 67,
      "type": "新课",
      "teacher": {
        "avatar": "https://img1.sycdn.imooc.com/user/5abe468b0001664107390741-100-100.jpg",
        "name": "DellLee"
      },
      "lastUpdate": "",
      "title": "前端要学的测试课 从Jest入门到 TDD/BDD双实战",
      "rank": "中级",
      "number": 157,
      "comment": 6,
      "desc": "以Vue/React项目进行自动化测试实战，让你技术水平和架构思维双提升",
      "isDiscount": false,
      "newPrice": "",
      "oldPrice": "299.00",
      "isLike": false
    },
    {
      "img": "https://img1.sycdn.imooc.com/szimg/5d396b990811a64706000338-360-202.jpg",
      "rate": 0,
      "type": "新课",
      "teacher": {
        "avatar": "https://img1.sycdn.imooc.com/user/5b40c3d8000153d311101084-100-100.jpg",
        "name": "Sam"
      },
      "lastUpdate": "",
      "title": "前端要学的测试课 从Jest入门到 TDD/BDD双实战",
      "rank": "初级",
      "number": 64,
      "comment": 5,
      "desc": "最新 mpvue2.0 框架 - 实战小慕读书多平台小程序",
      "isDiscount": true,
      "newPrice": "226.00",
      "oldPrice": "266.00",
      "isLike": false
    },
    {
      "img": "https://img1.sycdn.imooc.com/szimg/5c7e6835087ef3d806000338-360-202.jpg",
      "rate": 0,
      "type": "热门",
      "teacher": {
        "avatar": "https://img1.sycdn.imooc.com/user/545847e20001163c02200220-100-100.jpg",
        "name": "CrazyCodeBoy"
      },
      "lastUpdate": "3天前",
      "title": "Flutter从入门到进阶 实战携程网App",
      "rank": "中级",
      "number": 1495,
      "comment": 383,
      "desc": "从入门到进阶，系统掌握Flutter开发核心技术",
      "isDiscount": false,
      "newPrice": "",
      "oldPrice": "348.00",
      "isLike": true
    },
    {
      "img": "https://img1.sycdn.imooc.com/szimg/5d08d0b308c9749706000338-360-202.jpg",
      "rate": 0,
      "type": "",
      "teacher": {
        "avatar": "https://img1.sycdn.imooc.com/user/5afe3d350001596a02430243-100-100.jpg",
        "name": "神思者l"
      },
      "lastUpdate": "",
      "title": "阿里新零售数据库设计与实战",
      "rank": "初级",
      "number": 551,
      "comment": 37,
      "desc": "数据库是开发人员的必修课，解锁“新零售”业务让数据库实战能力再上一层楼",
      "isDiscount": false,
      "newPrice": "",
      "oldPrice": "288.00",
      "isLike": false
    },
    {
      "img": "https://img1.sycdn.imooc.com/szimg/5d14215f08545a6b06000338-360-202.jpg",
      "rate": 0,
      "type": "热门",
      "teacher": {
        "avatar": "https://img1.sycdn.imooc.com/user/5d142f090804929712361209-100-100.jpg",
        "name": "大目"
      },
      "lastUpdate": "",
      "title": "Spring Cloud Alibaba微服务从入门到进阶",
      "rank": "高级",
      "number": 339,
      "comment": 21,
      "desc": "面向未来微服务:熟练掌握Spring Cloud Alibaba",
      "isDiscount": false,
      "newPrice": "",
      "oldPrice": "399.00",
      "isLike": false
    },
    {
      "img": "https://img1.sycdn.imooc.com/szimg/5d2e7ada09946f6f12000676-360-202.jpg",
      "rate": 0,
      "type": "新课",
      "teacher": {
        "avatar": "https://img1.sycdn.imooc.com/user/5c36c432000158e609600960-100-100.jpg",
        "name": "张勤一"
      },
      "lastUpdate": "2019.7.17",
      "title": "基于Spring Cloud微服务架构  广告系统设计与实现（经典升级）",
      "rank": "中级",
      "number": 905,
      "comment": 270,
      "desc": "掌握互联网广告系统，学会为公司创收，你自然就是最抢手的人才。可用于毕设。",
      "isDiscount": false,
      "newPrice": "",
      "oldPrice": "299.00",
      "isLike": false
    },
    {
      "img": "https://img1.sycdn.imooc.com/szimg/5d2820fd0874bbf806000338-360-202.jpg",
      "rate": 0,
      "type": "新课",
      "teacher": {
        "avatar": "https://img1.sycdn.imooc.com/user/57df9bcd000195e810231024-100-100.jpg",
        "name": "Mushishi_Xu"
      },
      "lastUpdate": "",
      "title": "Python接口自动化测试框架实战 从设计到开发",
      "rank": "中级",
      "number": 52,
      "comment": 2,
      "desc": "从基础开始掌握接口自动化测试框架的设计与开发，并教你如何开发桩服务 ",
      "isDiscount": false,
      "newPrice": "",
      "oldPrice": "299.00",
      "isLike": false
    },
    {
      "img": "https://img1.sycdn.imooc.com/szimg/5d25400a08fa408c06000338-360-202.jpg",
      "rate": 0,
      "type": "新课",
      "teacher": {
        "avatar": "https://img1.sycdn.imooc.com/user/5c20a1bc0001b02506760800-100-100.jpg",
        "name": "xiangzepro"
      },
      "lastUpdate": "2019.07.10",
      "title": "毕设神器 Java主流技术栈SSM+SpringBoot商铺系统（升级更新）",
      "rank": "初级",
      "number": 2587,
      "comment": 636,
      "desc": "SSM商铺系统V1.0，解决毕业设计痛点；SpringBoot商铺V2.0，满足企业工作刚需",
      "isDiscount": false,
      "newPrice": "",
      "oldPrice": "299.00",
      "isLike": false
    },
    {
      "img": "https://img1.sycdn.imooc.com/szimg/5d1eb552082e176e06000338-360-202.jpg",
      "rate": 0,
      "type": "新课",
      "teacher": {
        "avatar": "https://img1.sycdn.imooc.com/user/533e4d510001c2ad02000200-100-100.jpg",
        "name": "Michael__PK"
      },
      "lastUpdate": "",
      "title": "Spark进阶 大数据离线与实时项目实战",
      "rank": "中级",
      "number": 96,
      "comment": 6,
      "desc": "大数据生态圈中多个框架(Spark/Hbase/Redis/Hadoop)的整合应用及调优",
      "isDiscount": false,
      "newPrice": "",
      "oldPrice": "399.00",
      "isLike": false
    },
    {
      "img": "https://img1.sycdn.imooc.com/szimg/5d1ad17f08cd16e800000000-360-202.jpg",
      "rate": 0,
      "type": "",
      "teacher": {
        "avatar": "https://img1.sycdn.imooc.com/user/5cac7e810001fe7705270698-100-100.jpg",
        "name": "城南大师兄"
      },
      "lastUpdate": "",
      "title": "Zookeeper源码分析",
      "rank": "中级",
      "number": 59,
      "comment": 4,
      "desc": "“分而治之”逐一攻克Zookeeper框架各个组件的源码",
      "isDiscount": false,
      "newPrice": "",
      "oldPrice": "388.00",
      "isLike": false
    }
  ]
}